[
  {
    "date": "July 7, 2026",
    "title": "Is Japan Really Out of Its Lost Decades, or Drifting Into Another One?",
    "summary": "Japan’s problem has never been the shock itself.",
    "url": "https://johnnykao.substack.com/p/japan-part-1-lost-decades-or-another-one"
  },
  {
    "date": "July 7, 2026",
    "title": "Yen Weakness Is Not Just a Dollar Story: Japan Is Facing an Entire System of External Pressures",
    "summary": "Widening U.S.-Japan rate differentials pull capital out of the yen.",
    "url": "https://johnnykao.substack.com/p/japan-part-2-yen-weakness-external-pressures"
  },
  {
    "date": "July 7, 2026",
    "title": "External Pressure Is Universal. Why Does Japan Bear It So Much More Heavily?",
    "summary": "The yen is not weak simply because the outside world has turned harsher.",
    "url": "https://johnnykao.substack.com/p/japan-part-3-why-japan-bears-it-more"
  },
  {
    "date": "July 7, 2026",
    "title": "Japan Has Spent a Great Deal. But Has It Bought Any Future Capacity?",
    "summary": "Subsidies can be justified in an emergency.",
    "url": "https://johnnykao.substack.com/p/japan-part-4-has-it-bought-future-capacity"
  },
  {
    "date": "July 7, 2026",
    "title": "Who Captures the Gains of a Weak Yen, and Who Pays the Bill?",
    "summary": "A weak yen is not a neutral national event that everyone shares equally.",
    "url": "https://johnnykao.substack.com/p/japan-part-5-who-benefits-from-a-weak-yen"
  }
]
